[
	{
		"__TYPE__": "SharedSliceContent",
		"variation": "default",
		"primary": {
			"title": {
				"__TYPE__": "StructuredTextContent",
				"value": [
					{
						"type": "paragraph",
						"content": {
							"text": "Cillum id esse minim excepteur aliqua sit consectetur ullamco commodo consequat dolor amet adipisicing consequat cupidatat. Quis ut ipsum ut nostrud nisi culpa ut aliqua deserunt qui."
						}
					}
				]
			},
			"description": {
				"__TYPE__": "StructuredTextContent",
				"value": [
					{
						"type": "paragraph",
						"content": {
							"text": "Eiusmod eiusmod est quis amet ad nisi do laboris laborum aliqua exercitation. Consequat aliquip cupidatat deserunt tempor ea aute."
						}
					}
				]
			},
			"options": {
				"__TYPE__": "GroupContentType",
				"value": [
					{
						"__TYPE__": "GroupItemContent",
						"value": [
							[
								"image",
								{
									"origin": {
										"id": "main",
										"url": "https://images.unsplash.com/photo-1560762484-813fc97650a0",
										"width": 3344,
										"height": 2509
									},
									"url": "https://images.unsplash.com/photo-1560762484-813fc97650a0",
									"width": 3344,
									"height": 2509,
									"edit": {
										"zoom": 1,
										"crop": {
											"x": 0,
											"y": 0
										},
										"background": "transparent"
									},
									"alt": "native",
									"credits": null,
									"__TYPE__": "ImageContent",
									"thumbnails": {}
								}
							],
							[
								"title",
								{
									"__TYPE__": "StructuredTextContent",
									"value": [
										{
											"type": "paragraph",
											"content": {
												"text": "Voluptate consequat elit quis excepteur exercitation exercitation."
											}
										}
									]
								}
							],
							[
								"texttopbanner",
								{
									"__TYPE__": "StructuredTextContent",
									"value": [
										{
											"type": "paragraph",
											"content": {
												"text": "Minim velit nostrud est labore nostrud elit ad Lorem eiusmod. Excepteur aliquip culpa consectetur sint cillum aute pariatur irure aliqua exercitation reprehenderit tempor. Tempor incididunt mollit voluptate deserunt quis consectetur sint."
											}
										}
									]
								}
							]
						]
					}
				]
			}
		},
		"items": []
	},
	{
		"__TYPE__": "SharedSliceContent",
		"variation": "twoColumns",
		"primary": {
			"options": {
				"__TYPE__": "GroupContentType",
				"value": [
					{
						"__TYPE__": "GroupItemContent",
						"value": [
							[
								"image",
								{
									"origin": {
										"id": "main",
										"url": "https://images.unsplash.com/photo-1587613865763-4b8b0d19e8ab",
										"width": 12288,
										"height": 16384
									},
									"url": "https://images.unsplash.com/photo-1587613865763-4b8b0d19e8ab",
									"width": 12288,
									"height": 16384,
									"edit": {
										"zoom": 1,
										"crop": {
											"x": 0,
											"y": 0
										},
										"background": "transparent"
									},
									"alt": "believed",
									"credits": null,
									"__TYPE__": "ImageContent",
									"thumbnails": {}
								}
							],
							[
								"title",
								{
									"__TYPE__": "StructuredTextContent",
									"value": [
										{
											"type": "paragraph",
											"content": {
												"text": "Laboris minim laboris exercitation sit. Dolore esse culpa officia qui commodo in non nulla elit."
											}
										}
									]
								}
							],
							[
								"subtitle",
								{
									"__TYPE__": "StructuredTextContent",
									"value": [
										{
											"type": "paragraph",
											"content": {
												"text": "Non excepteur anim aliqua pariatur aliqua irure. Dolore minim qui cillum non non dolore voluptate mollit laboris laborum mollit ut dolore."
											}
										}
									]
								}
							],
							[
								"buttontext",
								{
									"__TYPE__": "FieldContent",
									"value": "location",
									"type": "Text"
								}
							],
							[
								"buttonlink",
								{
									"key": "a494f117-66e4-499c-b71f-e1fe8bb9bbd4",
									"__TYPE__": "LinkContent",
									"value": {
										"__TYPE__": "ExternalLink",
										"url": "http://twitter.com",
										"text": "boy"
									}
								}
							]
						]
					}
				]
			}
		},
		"items": [
			{
				"__TYPE__": "GroupItemContent",
				"value": []
			}
		]
	}
]